ACKNOWLEDGEMENTS
AUTHORS
LICENSE
MANIFEST.in
README
dependencies.ini
pyproject.toml
requirements.txt
run_tests.py
setup.cfg
setup.py
test_requirements.txt
config/appveyor/install.ps1
config/appveyor/install.sh
config/appveyor/runtests.sh
config/dpkg/changelog
config/dpkg/clean
config/dpkg/compat
config/dpkg/control
config/dpkg/copyright
config/dpkg/dfimagetools-tools.install
config/dpkg/python3-dfimagetools.install
config/dpkg/rules
config/dpkg/source/format
config/pylint/spelling-private-dict
dfimagetools/__init__.py
dfimagetools/artifact_filters.py
dfimagetools/bodyfile.py
dfimagetools/data_stream_writer.py
dfimagetools/decorators.py
dfimagetools/definitions.py
dfimagetools/environment_variables.py
dfimagetools/file_entry_lister.py
dfimagetools/path_filters.py
dfimagetools/path_resolver.py
dfimagetools/recursive_hasher.py
dfimagetools/resources.py
dfimagetools/source_analyzer.py
dfimagetools/windows_registry.py
dfimagetools.egg-info/PKG-INFO
dfimagetools.egg-info/SOURCES.txt
dfimagetools.egg-info/dependency_links.txt
dfimagetools.egg-info/entry_points.txt
dfimagetools.egg-info/requires.txt
dfimagetools.egg-info/top_level.txt
dfimagetools/helpers/__init__.py
dfimagetools/helpers/backend.py
dfimagetools/helpers/command_line.py
dfimagetools/scripts/__init__.py
dfimagetools/scripts/extract_data_streams.py
dfimagetools/scripts/list_file_entries.py
dfimagetools/scripts/map_extents.py
dfimagetools/scripts/recursive_hasher.py
dfimagetools/scripts/source_analyzer.py
test_data/image.qcow2
test_data/ntfs.vhd
test_data/ntfs.vhd.bodyfile
test_data/artifacts/artifacts.yaml
tests/__init__.py
tests/artifact_filters.py
tests/bodyfile.py
tests/data_stream_writer.py
tests/environment_variables.py
tests/file_entry_lister.py
tests/path_filters.py
tests/path_resover.py
tests/source_analyzer.py
tests/test_lib.py
utils/__init__.py
utils/check_dependencies.py
utils/dependencies.py